pyechartsWithTitleRetrievable/__init__.py
pyechartsWithTitleRetrievable/_version.py
pyechartsWithTitleRetrievable-0.0.2.dist-info/LICENSE
pyechartsWithTitleRetrievable-0.0.2.dist-info/METADATA
pyechartsWithTitleRetrievable-0.0.2.dist-info/WHEEL
pyechartsWithTitleRetrievable-0.0.2.dist-info/top_level.txt
pyechartsWithTitleRetrievable-0.0.2.dist-info/RECORD
